dlsys/__init__.py
dlsys/dlsys.py
dlsys-2.0.0.dist-info/LICENSE
dlsys-2.0.0.dist-info/METADATA
dlsys-2.0.0.dist-info/WHEEL
dlsys-2.0.0.dist-info/top_level.txt
dlsys-2.0.0.dist-info/RECORD
