Metadata-Version: 2.1
Name: dlsys
Version: 2.0.0
Summary: A versatile downloader for various types of internet content
Home-page: https://github.com/yourusername/dlsys
Author: Your Name
Author-email: your.email@example.com
Classifier: Development Status :: 3 - Alpha
Classifier: Intended Audience :: Developers
Classifier: License :: OSI Approved :: MIT License
Classifier: Operating System :: OS Independent
Classifier: Programming Language :: Python :: 3
Classifier: Programming Language :: Python :: 3.7
Classifier: Programming Language :: Python :: 3.8
Classifier: Programming Language :: Python :: 3.9
Classifier: Programming Language :: Python :: 3.10
Classifier: Programming Language :: Python :: 3.11
Requires-Python: >=3.7
License-File: LICENSE
Requires-Dist: yt-dlp
Requires-Dist: requests
Requires-Dist: pydub
